Weather_cmd/__init__.py
Weather_cmd-0.0.1.dist-info/LICENCE.txt
Weather_cmd-0.0.1.dist-info/METADATA
Weather_cmd-0.0.1.dist-info/WHEEL
Weather_cmd-0.0.1.dist-info/top_level.txt
Weather_cmd-0.0.1.dist-info/RECORD
